inputless_models/__init__.py
inputless_models/anomaly_detection.py
inputless_models/features/__init__.py
inputless_models/features/behavioral_dna_profiling.py
inputless_models/features/predictive_behavior_models.py
inputless_models/features/real_time_anomaly_alerts.py
inputless_models/model_training.py
inputless_models/pattern_recognition.py
inputless_models/predictive_analytics.py
inputless_models/types.py
inputless_models-1.0.2.dist-info/METADATA
inputless_models-1.0.2.dist-info/WHEEL
inputless_models-1.0.2.dist-info/RECORD
